<?xml version="1.0" encoding="utf-8"?>
<Defs>
	<AbilityDef>
		<defName>MetalbloodSurge</defName>
		<label>crimson steel infusion</label>
		<description>Activate the metalblood heart implant to surge liquid metal through the bloodstream, creating a temporary fusion of flesh and steel. This enhancement dramatically reduces incoming damage as the body becomes partially mechanized, though the effect fades as the metallic compounds are naturally filtered out.</description>
		<iconPath>UI/Abilities/MetalbloodInjection</iconPath>
		<cooldownTicksRange>15000</cooldownTicksRange>
		<hostile>false</hostile>
		<groupAbility>true</groupAbility>
		<displayGizmoWhileUndrafted>true</displayGizmoWhileUndrafted>
		<disableGizmoWhileUndrafted>false</disableGizmoWhileUndrafted>
		<aiCanUse>true</aiCanUse>
		<ai_IsOffensive>true</ai_IsOffensive>
		<targetRequired>false</targetRequired>
		<casterMustBeCapableOfViolence>false</casterMustBeCapableOfViolence>
		<statBases>
			<Ability_Duration>120</Ability_Duration>
		</statBases>
		<charges>6</charges>
		<cooldownPerCharge>true</cooldownPerCharge>
		<verbProperties>
			<verbClass>Verb_CastAbility</verbClass>
			<drawAimPie>false</drawAimPie>
			<requireLineOfSight>false</requireLineOfSight>
			<nonInterruptingSelfCast>true</nonInterruptingSelfCast>
			<soundCast>Pawn_Ghoul_Frenzy</soundCast>
			<targetable>false</targetable>
			<targetParams>
				<canTargetSelf>true</canTargetSelf>
			</targetParams>
		</verbProperties>
		<comps>
			<li Class="CompProperties_AbilityGiveHediff">
				<compClass>CompAbilityEffect_GiveHediff</compClass>
				<hediffDef>Metalblood</hediffDef>
				<onlyApplyToSelf>True</onlyApplyToSelf>
				<replaceExisting>true</replaceExisting>
			</li>
		</comps>
	</AbilityDef>
	<AbilityDef Name="ShapeFlesh">
		<defName>ChaosCall</defName>
		<label>flesh sculptor</label>
		<description>Invoke a malevolent archotech intelligence to reanimate a corpse into a grotesque fleshbeast. The dark transformation twists dead tissue into a nightmarish creature driven by pure aggression. The resulting monstrosity will attack all living beings indiscriminately, including its creator.</description>
		<iconPath>UI/Abilities/ShapeFlesh</iconPath>
		<cooldownTicksRange>3600</cooldownTicksRange>
		<charges>9</charges>
		<cooldownPerCharge>true</cooldownPerCharge>
		<showPsycastEffects>false</showPsycastEffects>
		<sendMessageOnCooldownComplete>true</sendMessageOnCooldownComplete>
		<displayGizmoWhileUndrafted>true</displayGizmoWhileUndrafted>
		<disableGizmoWhileUndrafted>false</disableGizmoWhileUndrafted>
		<moteOffsetAmountTowardsTarget>0.5</moteOffsetAmountTowardsTarget>
		<warmupMote>Mote_HoraxSmallSpellWarmup</warmupMote>
		<warmupEffecter>HoraxianAbilityCasting</warmupEffecter>
		<warmupSound>AnomalyAbilityWarmup</warmupSound>
		<casterMustBeCapableOfViolence>false</casterMustBeCapableOfViolence>
		<verbProperties>
			<verbClass>Verb_CastAbility</verbClass>
			<warmupTime>2</warmupTime>
			<range>99</range>
			<requireLineOfSight>True</requireLineOfSight>
			<drawHighlightWithLineOfSight>true</drawHighlightWithLineOfSight>
			<targetParams>
				<canTargetSelf>false</canTargetSelf>
				<canTargetMechs>false</canTargetMechs>
				<canTargetBuildings>false</canTargetBuildings>
				<canTargetCorpses>true</canTargetCorpses>
				<onlyTargetCorpses>true</onlyTargetCorpses>
			</targetParams>
		</verbProperties>
		<comps>
			<li Class="CompProperties_FleshbeastFromCorpse" />
		</comps>
	</AbilityDef>
	<AbilityDef>
		<defName>CommandSlaughter</defName>
		<label>flesh dissolution</label>
		<description>Unleash a devastating psychic assault that causes catastrophic cellular breakdown in living tissue. The target's flesh rapidly deteriorates and reforms into a twisted mass of organic matter, killing them instantly through horrific biological reconstruction. This ability represents the pinnacle of flesh manipulation techniques.</description>
		<iconPath>UI/Abilities/Slaughter</iconPath>
		<cooldownTicksRange>180000</cooldownTicksRange>
		<showPsycastEffects>false</showPsycastEffects>
		<sendMessageOnCooldownComplete>true</sendMessageOnCooldownComplete>
		<stunTargetWhileCasting>true</stunTargetWhileCasting>
		<moteOffsetAmountTowardsTarget>0.5</moteOffsetAmountTowardsTarget>
		<warmupMote>Mote_HoraxSmallSpellWarmup</warmupMote>
		<warmupEffecter>HoraxianAbilityCasting</warmupEffecter>
		<warmupSound>AnomalyAbilityWarmup</warmupSound>
		<writeCombatLog>true</writeCombatLog>
		<charges>8</charges>
		<cooldownPerCharge>true</cooldownPerCharge>
		<verbProperties>
			<verbClass>Verb_CastAbility</verbClass>
			<warmupTime>2</warmupTime>
			<range>99</range>
			<requireLineOfSight>false</requireLineOfSight>
			<drawHighlightWithLineOfSight>true</drawHighlightWithLineOfSight>
			<targetParams>
				<canTargetBuildings>false</canTargetBuildings>
				<canTargetMechs>false</canTargetMechs>
			</targetParams>
		</verbProperties>
		<comps>
			<li Class="CompProperties_PsychicSlaughter" />
		</comps>
	</AbilityDef>
</Defs>
